odoo8_addon_secure_uninstall-8.0.1.0.0.99.dev20-nspkg.pth
odoo_addons/secure_uninstall/README.rst
odoo_addons/secure_uninstall/__init__.py
odoo_addons/secure_uninstall/__openerp__.py
odoo_addons/secure_uninstall/i18n/ca.po
odoo_addons/secure_uninstall/i18n/de.po
odoo_addons/secure_uninstall/i18n/es.po
odoo_addons/secure_uninstall/i18n/fr.po
odoo_addons/secure_uninstall/i18n/it.po
odoo_addons/secure_uninstall/i18n/pt_BR.po
odoo_addons/secure_uninstall/i18n/secure_uninstall.pot
odoo_addons/secure_uninstall/i18n/sl.po
odoo_addons/secure_uninstall/i18n/tr.po
odoo_addons/secure_uninstall/models/__init__.py
odoo_addons/secure_uninstall/models/module.py
odoo_addons/secure_uninstall/static/description/icon.png
odoo_addons/secure_uninstall/static/description/img1.png
odoo_addons/secure_uninstall/tests/__init__.py
odoo_addons/secure_uninstall/tests/test_uninstall.py
odoo_addons/secure_uninstall/views/module_view.xml
odoo8_addon_secure_uninstall-8.0.1.0.0.99.dev20.dist-info/METADATA
odoo8_addon_secure_uninstall-8.0.1.0.0.99.dev20.dist-info/WHEEL
odoo8_addon_secure_uninstall-8.0.1.0.0.99.dev20.dist-info/namespace_packages.txt
odoo8_addon_secure_uninstall-8.0.1.0.0.99.dev20.dist-info/top_level.txt
odoo8_addon_secure_uninstall-8.0.1.0.0.99.dev20.dist-info/RECORD
